setup.py
library_unareti.egg-info/PKG-INFO
library_unareti.egg-info/SOURCES.txt
library_unareti.egg-info/dependency_links.txt
library_unareti.egg-info/top_level.txt
unareti/__init__.py
unareti/rpt2csv_unareti.py
unareti/unareti_data_manager.py