Metadata-Version: 1.1
Name: library-unareti
Version: 1.0
Summary: python library for unareti data managing
Home-page: UNKNOWN
Author: Davide Beretta, PhD, RSE
Author-email: davide.beretta@rse-web.it
License: MIT
Keywords: data manager unareti
Platform: UNKNOWN
Classifier: Development Status :: 3 - Alpha
Classifier: Intended Audience :: Developers
Classifier: Topic :: Software Development :: Build Tools
Classifier: License :: OSI Approved :: MIT License
Classifier: Programming Language :: Python :: 2
Classifier: Programming Language :: Python :: 2.7
Classifier: Programming Language :: Python :: 3
Classifier: Programming Language :: Python :: 3.3
Classifier: Programming Language :: Python :: 3.4
Classifier: Programming Language :: Python :: 3.5
